Metadata-Version: 1.1
Name: hq
Version: 0.0.4
Summary: Command-line tool for querying, slicing & dicing HTML using the XPath/XQuery derivative HQuery.
Home-page: https://github.com/rbwinslow/hq
Author: Richard B. Winslow
Author-email: richard.b.winslow@gmail.com
License: MIT
Keywords: html xpath query xquery hquery jq cmdline cli
Platform: UNKNOWN
Classifier: Development Status :: 2 - Pre-Alpha
Classifier: Intended Audience :: Developers
Classifier: Environment :: Console
Classifier: License :: OSI Approved :: MIT License
Classifier: Programming Language :: Python
Classifier: Topic :: Text Processing :: Markup :: HTML
